simpled/__init__.py
simpled-0.0.0.dist-info/METADATA
simpled-0.0.0.dist-info/WHEEL
simpled-0.0.0.dist-info/top_level.txt
simpled-0.0.0.dist-info/RECORD
